MANIFEST.in
__init__.py
database.py
setup.py
models/_init__.py
models/broker.py
models/symbol.py
shared_models_stocksblitz.egg-info/PKG-INFO
shared_models_stocksblitz.egg-info/SOURCES.txt
shared_models_stocksblitz.egg-info/dependency_links.txt
shared_models_stocksblitz.egg-info/requires.txt
shared_models_stocksblitz.egg-info/top_level.txt