Metadata-Version: 2.1
Name: shared_models_stocksblitz
Version: 0.1.5
Requires-Dist: sqlalchemy
Requires-Dist: psycopg2
